{
  "id": "perfect-accuracy-achievement",
  "category": "Core",
  "title": "Perfect Accuracy Achievement",
  "description": "Award achievement when user achieves 100% accuracy on any test. Validate accuracy calculation and trigger achievement on test completion.",
  "status": "backlog",
  "priority": 2,
  "complexity": "simple",
  "dependencies": [
    "achievement-definition-system",
    "test-completion-handler"
  ],
  "createdAt": "2025-12-29T10:34:07.044Z",
  "updatedAt": "2025-12-29T10:34:07.044Z"
}