{
  "id": "user-auth-system",
  "category": "Authentication",
  "title": "User Authentication System",
  "description": "Implement user registration, login, and session management using TanStack Start's built-in auth capabilities. Store user credentials securely and manage user sessions.",
  "status": "verified",
  "priority": 1,
  "complexity": "moderate",
  "dependencies": [
    "database-schema-setup"
  ],
  "createdAt": "2025-12-29T10:34:07.038Z",
  "updatedAt": "2025-12-29T11:18:53.461Z",
  "branchName": "main",
  "startedAt": "2025-12-29T11:04:48.949Z"
}