{
  "id": "optimize-leaderboard-performance",
  "category": "UI",
  "title": "Optimize Leaderboard Performance with Virtual Scrolling",
  "description": "Implement virtual scrolling for the leaderboard to handle large lists efficiently. Add caching and pagination to reduce database load and improve initial load times.",
  "status": "verified",
  "priority": 2,
  "complexity": "moderate",
  "dependencies": [],
  "createdAt": "2026-01-20T19:10:28.532Z",
  "updatedAt": "2026-01-20T19:28:26.519Z",
  "branchName": "feats",
  "startedAt": "2026-01-20T19:11:18.977Z"
}